treg.py
treg-0.0.3.dist-info/METADATA
treg-0.0.3.dist-info/WHEEL
treg-0.0.3.dist-info/top_level.txt
treg-0.0.3.dist-info/RECORD
