Metadata-Version: 2.1
Name: treg
Version: 0.0.3
Summary: treg utilizes trie structured regex patterns to search texts for a potientially large number of words and phrases.
Home-page: https://https://github.com/RaphaelBoegel/Tregex
Author: Raphael Bögel
Author-email: raphael.boegel@gmail.com
License: UNKNOWN
Platform: UNKNOWN
Classifier: Programming Language :: Python :: 3
Classifier: License :: OSI Approved :: MIT License
Classifier: Operating System :: OS Independent
Requires-Python: >=3.7
